gpu_tracker/__init__.py
gpu_tracker/__main__.py
gpu_tracker/_helper_classes.py
gpu_tracker/_version.py
gpu_tracker/sub_tracker.py
gpu_tracker/tracker.py
gpu_tracker-5.0.1.dist-info/licenses/LICENSE
gpu_tracker-5.0.1.dist-info/METADATA
gpu_tracker-5.0.1.dist-info/WHEEL
gpu_tracker-5.0.1.dist-info/entry_points.txt
gpu_tracker-5.0.1.dist-info/top_level.txt
gpu_tracker-5.0.1.dist-info/RECORD
