Metadata-Version: 2.4
Name: gpu-tracker
Version: 5.0.1
Summary: Tracks computational resources of a process and its child processes, most prominently GPU RAM, as well as RAM, compute time, and CPU utilization.
License: The Clear BSD License
Project-URL: Homepage, https://github.com/MoseleyBioinformaticsLab/gpu_tracker
Project-URL: Documentation, https://moseleybioinformaticslab.github.io/gpu_tracker/
Project-URL: GitHub, https://github.com/MoseleyBioinformaticsLab/gpu_tracker
Project-URL: Issues, https://github.com/MoseleyBioinformaticsLab/gpu_tracker/issues
Keywords: gpu,ram,time,memory,profile,track,resource,usage
Classifier: Environment :: Console
Classifier: Environment :: GPU :: NVIDIA CUDA
Classifier: Intended Audience :: Developers
Classifier: License :: OSI Approved :: BSD License
Classifier: Operating System :: OS Independent
Classifier: Programming Language :: Python :: 3.10
Classifier: Topic :: Software Development :: Libraries :: Python Modules
Classifier: Topic :: System :: Hardware
Classifier: Topic :: System :: Monitoring
Classifier: Typing :: Typed
Requires-Python: >=3.10
License-File: LICENSE
Requires-Dist: psutil>=6.0.0
Requires-Dist: docopt>=0.6.2
Requires-Dist: pandas>=2.2.3
Requires-Dist: SQLAlchemy>=2.0.39
Requires-Dist: tqdm>=4.67.1
Dynamic: license-file
